sharepointlib_dq/__init__.py
sharepointlib_dq/core/__init__.py
sharepointlib_dq/core/exceptions.py
sharepointlib_dq/core/metadata.py
sharepointlib_dq/core/writer.py
sharepointlib_dq/notifier/__init__.py
sharepointlib_dq/notifier/sender.py
sharepointlib_dq/notifier/templates.py
sharepointlib_dq-0.0.1.dist-info/licenses/LICENSE
sharepointlib_dq-0.0.1.dist-info/METADATA
sharepointlib_dq-0.0.1.dist-info/WHEEL
sharepointlib_dq-0.0.1.dist-info/top_level.txt
sharepointlib_dq-0.0.1.dist-info/RECORD
