Metadata-Version: 2.4
Name: sharepointlib_dq
Version: 0.0.1
Summary: A library providing a standardised data quality tracking in lakehouse environments. Designed for use within Databricks, where PySpark is already available.
Author-email: Paulo Portela <portela.paulo@gmail.com>
Maintainer-email: Paulo Portela <portela.paulo@gmail.com>
License-Expression: BSD-3-Clause
Project-URL: Homepage, https://github.com/aghuttun/sharepointlib_dq
Project-URL: Documentation, https://github.com/aghuttun/sharepointlib_dq/blob/main/README.md
Keywords: SharePoint,DQ,Python,Configuration,Lakehouse,DataBricks
Classifier: Programming Language :: Python :: 3.10
Classifier: Programming Language :: Python :: 3.11
Classifier: Programming Language :: Python :: 3.12
Classifier: Programming Language :: Python :: 3.13
Classifier: Programming Language :: Python :: 3.14
Classifier: Programming Language :: Python :: Implementation :: CPython
Classifier: Intended Audience :: Developers
Classifier: Operating System :: POSIX :: Linux
Classifier: Operating System :: Microsoft :: Windows
Classifier: Operating System :: MacOS
Classifier: Operating System :: MacOS :: MacOS X
Requires-Python: >=3.10
License-File: LICENSE
Requires-Dist: requests
Provides-Extra: dev
Requires-Dist: twine; extra == "dev"
Requires-Dist: build; extra == "dev"
Provides-Extra: spark
Requires-Dist: pyspark>=3.5.0; extra == "spark"
Dynamic: license-file
